marga_pulseq/__init__.py
marga_pulseq/interpreter.py
marga_pulseq-0.2.2.dist-info/LICENSE
marga_pulseq-0.2.2.dist-info/METADATA
marga_pulseq-0.2.2.dist-info/WHEEL
marga_pulseq-0.2.2.dist-info/top_level.txt
marga_pulseq-0.2.2.dist-info/RECORD
