Metadata-Version: 2.1
Name: marga_pulseq
Version: 0.2.2
Summary: A simple interpreter from PulSeq 1.4 to MARGA
Home-page: https://github.com/marcos-mri/marga_pulseq
Author: Lincoln Craven-Brightman,Benjamin Menkuec,José Miguel Algarín
Author-email: lcraven-brightman@mgh.harvard.edu,benjamin.menkuec@fh-dortmund.dejosalggui@i3m.upv.es
License: MIT
Classifier: Operating System :: OS Independent
Classifier: Programming Language :: Python
Requires-Python: >=3.6
License-File: LICENSE
